{
    "id": 10402,
    "name": "圣战士登拜因",
    "image_path": "frontend/data/images/10402.jpg",
    "points": 7.6,
    "cost": 1,
    "rarity": "N",
    "description": "《圣战士登拜因》宫武一贵作品，其中运用当时最先进技术创造出了“有机生态兵器”的前身。这次的“福音战士”从某种程度上也可以说是它的延续。圣战士：拜斯顿.威尔古传说中记载的拯救世界的战士。拜斯顿.威尔的古门人中流传着圣战士曾经显现奇迹，击败了企图统治拜斯顿.威尔的邪恶势力的传说。而来成为为了被召唤到拜斯顿.威尔，能驾驶奥拉机械，拥有比一般古门人更强“潜在能力”的地上人们的称号.....",
    "type": 2,
    "platform": "TV",
    "episodes_for_hangup": 49,
    "synergy_tags": [
        "科幻",
        "机战",
        "TV",
        "日本",
        "原创"
    ],
    "date": "1983-02-05",
    "rating_rank": 821,
    "rating_score": 7.6,
    "rating_total": 325
}