{
    "id": 29307,
    "type": 2,
    "name": "境界線上のホライゾンII",
    "name_cn": "境界线上的地平线 第二季",
    "summary": "剧情紧接前作展开，航空都市舰武藏在救出赫莱森·阿利亚达斯特之后，离开三河启航前往英国，希望能获得英国的支援。但由于无敌舰队海战历史再现开战在即，三征西班牙害怕英国与武藏联手，决定先声夺人攻击武藏。\r\n面对三征西班牙精锐攻击，武藏与之相对后顺利逃脱，但在英国边境却遭受英国“女王的盾符”成员攻击，不得已只好暂时与赫莱森等人搭乘的运输舰切割。运输舰总算是平安登陆在第四阶层的海岸，英国却不准武藏舰登陆。\r\n武藏与英国经过谈判，决定举办联合校庆，但后续发展依旧困难重重。\r\n而此时，点藏·库罗斯优奈特在海岸边遇到一个浑身伤痕的神秘人，解开了英国方面一段不为人知的隐情。\r\n故事由此展开。",
    "nsfw": false,
    "locked": false,
    "date": "2012-07-07",
    "platform": "TV",
    "images": {
        "large": "https://lain.bgm.tv/pic/cover/l/cb/e6/29307_h19Oo.jpg",
        "common": "https://lain.bgm.tv/r/400/pic/cover/l/cb/e6/29307_h19Oo.jpg",
        "medium": "https://lain.bgm.tv/r/800/pic/cover/l/cb/e6/29307_h19Oo.jpg",
        "small": "https://lain.bgm.tv/r/200/pic/cover/l/cb/e6/29307_h19Oo.jpg",
        "grid": "https://lain.bgm.tv/r/100/pic/cover/l/cb/e6/29307_h19Oo.jpg"
    },
    "infobox": [
        {
            "key": "中文名",
            "value": "境界线上的地平线 第二季"
        },
        {
            "key": "别名",
            "value": [
                {
                    "v": "境界線上のホライゾンⅡ",
                    "k": null
                },
                {
                    "v": "Horizon on the Middle of Nowhere Ⅱ",
                    "k": null
                }
            ]
        },
        {
            "key": "话数",
            "value": "13"
        },
        {
            "key": "放送开始",
            "value": "2012年7月7日"
        },
        {
            "key": "放送星期",
            "value": "星期六"
        },
        {
            "key": "官方网站",
            "value": "http://genesis-horizon.net/"
        },
        {
            "key": "播放结束",
            "value": "2012年9月29日"
        },
        {
            "key": "动画制作",
            "value": "サンライズ第8スタジオ"
        },
        {
            "key": "OP・ED 分镜",
            "value": "小野学（OP、ED3、ED4）、飯田恵理子（ED1）、田辺泰裕（ED2）"
        },
        {
            "key": "机械作画监督",
            "value": "川原智弘（OP、第二话、第十三话）、大塚健（第五话、第十二话）、佐野誉幸（第九话）"
        },
        {
            "key": "人物设定",
            "value": "藤井智之（兼アニメーションディレクター）、西澤真也、愛敬由紀子、鈴木勘太"
        },
        {
            "key": "特技监督",
            "value": "川原智弘"
        },
        {
            "key": "动作作画监督",
            "value": "鈴木勘太（第十话）"
        },
        {
            "key": "原作",
            "value": "川上稔（電擊文庫 刊）"
        },
        {
            "key": "製作",
            "value": "境界線上のホライゾン製作委員会 （サンライズ、バンダイビジュアル、アスキー・メディアワークス、ランティス、ソニーPCL）"
        }
    ],
    "volumes": 0,
    "eps": 13,
    "total_episodes": 13,
    "rating": {
        "rank": 821,
        "total": 3148,
        "count": {
            "one": 13,
            "two": 8,
            "three": 10,
            "four": 26,
            "five": 95,
            "six": 380,
            "seven": 940,
            "eight": 1070,
            "nine": 387,
            "ten": 219
        },
        "score": 7.5
    },
    "collection": {
        "wish": 1262,
        "collect": 4989,
        "doing": 273,
        "on_hold": 322,
        "dropped": 142
    },
    "tags": [
        {
            "name": "境界线上的地平线",
            "count": 681
        },
        {
            "name": "SUNRISE",
            "count": 529
        },
        {
            "name": "2012年7月",
            "count": 394
        },
        {
            "name": "轻小说改",
            "count": 303
        },
        {
            "name": "TV",
            "count": 282
        },
        {
            "name": "福山润",
            "count": 189
        },
        {
            "name": "裸王",
            "count": 183
        },
        {
            "name": "2012",
            "count": 156
        },
        {
            "name": "川上稔",
            "count": 145
        },
        {
            "name": "搞笑",
            "count": 145
        },
        {
            "name": "第二季",
            "count": 137
        },
        {
            "name": "二期",
            "count": 96
        },
        {
            "name": "贤姐",
            "count": 92
        },
        {
            "name": "战斗",
            "count": 82
        },
        {
            "name": "轻改",
            "count": 76
        },
        {
            "name": "小野学",
            "count": 51
        },
        {
            "name": "子安武人",
            "count": 32
        },
        {
            "name": "小说改",
            "count": 30
        },
        {
            "name": "科幻",
            "count": 30
        },
        {
            "name": "卖肉",
            "count": 27
        },
        {
            "name": "后宫",
            "count": 26
        },
        {
            "name": "奇幻",
            "count": 24
        },
        {
            "name": "七月番",
            "count": 17
        },
        {
            "name": "日本",
            "count": 16
        },
        {
            "name": "2012.7",
            "count": 13
        },
        {
            "name": "2012年",
            "count": 11
        },
        {
            "name": "萝卜",
            "count": 11
        },
        {
            "name": "肉",
            "count": 11
        },
        {
            "name": "续作",
            "count": 11
        },
        {
            "name": "燃",
            "count": 10
        }
    ],
    "meta_tags": [
        "TV",
        "日本",
        "战斗",
        "小说改"
    ],
    "series": false,
    "main_character_ids": [
        13182,
        13196,
        13204,
        13207
    ],
    "main_characters": [
        {
            "id": 13182,
            "name": "点蔵・クロスユナイト",
            "type": 1,
            "images": {
                "large": "https://lain.bgm.tv/pic/crt/l/96/fb/13182_crt_kx2L8.jpg",
                "medium": "https://lain.bgm.tv/r/400/pic/crt/l/96/fb/13182_crt_kx2L8.jpg",
                "small": "https://lain.bgm.tv/r/100/pic/crt/l/96/fb/13182_crt_kx2L8.jpg",
                "grid": "https://lain.bgm.tv/pic/crt/g/96/fb/13182_crt_kx2L8.jpg"
            },
            "relation": "主角",
            "actors": [
                {
                    "id": 4456,
                    "name": "小野大輔",
                    "type": 1,
                    "career": [
                        "artist",
                        "seiyu"
                    ],
                    "images": {
                        "large": "https://lain.bgm.tv/pic/crt/l/c4/8e/4456_prsn_HEQe3.jpg",
                        "medium": "https://lain.bgm.tv/r/400/pic/crt/l/c4/8e/4456_prsn_HEQe3.jpg",
                        "small": "https://lain.bgm.tv/r/100/pic/crt/l/c4/8e/4456_prsn_HEQe3.jpg",
                        "grid": "https://lain.bgm.tv/pic/crt/g/c4/8e/4456_prsn_HEQe3.jpg"
                    },
                    "short_summary": "在日本大学艺术学部放送学科就读时，主要是专攻电视节目制作。但因为当时提出的企划作品被教授评价的很差，所以转而改以演出者方式参与，并在参与过程中感受到演戏的有趣，因此决定以成为声优为目标。\r\n　　 出道当时，以动画节目的准常态出演（担任非固定角色名的小角色配音）为主。\r\n　　 第一部担任主角的动画作品是「AIR」TV动画版的男主角国崎往人。\r\n　　 在2006年放送的动画《凉宫春日的忧郁》以古泉一树这个角色获得广大知名度，其後也陆续获得许多要角演出。从帅气知性的青年到有点脱线的搞笑角色，演出的类型范围十分广泛。\r\n　　 2008年以《南家三姐妹》保坂这个角色获得第二回声优奖男优部门配角赏。　\r\n　　据来自2010年6月14日，IT世界网的咨询《Voice NewType投票，新一代声优崭露头角》中报道：男性榜单这边倒几乎都是老面孔，不过占据首位的再也不是福山润和神谷浩史等人，今次终于也轮到了小野大辅。长期以来如同劳模一般辛苦工作的小野大辅，如今终于名利双收，不但摘得上届声优大赏最佳男主角赏，如今人气投票又问鼎冠军，实在可喜可贺。\r\n　　 2010年1月31日その执事、狂騒～赤いヴァレンタイン声优见面会中被主持人吉田尚记称为声优界的谷原章介。\r\n　　 2010年3月以《黑执事》塞巴斯蒂安这个角色获得第四回声优奖主演男优赏。\r\n　　 2010年4月新番《迷糊餐馆working》中担任佐藤润的声优。\r\n　　 2010年4月新番《无法逃离的背叛》中担任莲城焰椎真的声优\r\n　　 2010年7月新番《传说中的勇者传说》中担任西昂·阿斯塔尔的声优。《黑执事2》中继续担任塞巴斯蒂安的声优。\r\n　　在《背叛》中的热血少年，《传说中的勇者传说》的拥有伟大理想又腹黑的西昂使小野大辅的声线变化发挥地更为淋漓尽致。",
                    "locked": false
                }
            ]
        },
        {
            "id": 13196,
            "name": "本多・正純",
            "type": 1,
            "images": {
                "large": "https://lain.bgm.tv/pic/crt/l/db/47/13196_crt_Bjj21.jpg",
                "medium": "https://lain.bgm.tv/r/400/pic/crt/l/db/47/13196_crt_Bjj21.jpg",
                "small": "https://lain.bgm.tv/r/100/pic/crt/l/db/47/13196_crt_Bjj21.jpg",
                "grid": "https://lain.bgm.tv/pic/crt/g/db/47/13196_crt_Bjj21.jpg"
            },
            "relation": "主角",
            "actors": [
                {
                    "id": 4244,
                    "name": "沢城みゆき",
                    "type": 1,
                    "career": [
                        "artist",
                        "seiyu"
                    ],
                    "images": {
                        "large": "https://lain.bgm.tv/pic/crt/l/96/b0/4244_prsn_Igahi.jpg?r=1687791526",
                        "medium": "https://lain.bgm.tv/r/400/pic/crt/l/96/b0/4244_prsn_Igahi.jpg?r=1687791526",
                        "small": "https://lain.bgm.tv/r/100/pic/crt/l/96/b0/4244_prsn_Igahi.jpg?r=1687791526",
                        "grid": "https://lain.bgm.tv/pic/crt/g/96/b0/4244_prsn_Igahi.jpg?r=1687791526"
                    },
                    "short_summary": "日本长野县出身的女性声优。昵称みゆきち(Miyukichi)，隶属青二Production事务所。\r\n\r\n1998年，Broccoli公司弄出一系列旗下精品店2D角色的策划，即猫耳女仆装萌LOLI角色商品的推广，并且在全国范围开展了还算有声势的“Di Gi Charat”角色声优遴选活动。那时候，初中二年级也是选手中年龄第二小的泽城美雪获得了评委特别奖，和得到冠军的真田麻美（真田アサミ）一起于“Di Gi Charat”声优出道。\r\n2001年，在动画《顽皮小白貂》中首次为主演角色配音。\r\n\r\n未进入过声优养成所的她经过同是D.U.P.成员的冰上恭子介绍，来到以外国影视吹替为特色的事务所Mausu Promotion，之后演技学习上得到了更好的指导，也获得了不少锻炼经验，可以明显地感觉她的声优本领技巧历精更始。\r\n2007年秋，成为Theatre剧团子的准剧团成员，开始了舞台剧的表演生涯。\r\n2009年，获得第三届声优奖助演女声优赏。获“以率真的表演为多部作品添色不少的实力派声优”的评价。\r\n2010年，获得第四届声优奖主演女声优赏。2010年全年，泽城的总演出电视动画集数是219话，即大约在每一季度，便有超过50话的动画都能听见她的声音。\r\n2011年，获得第五届声优奖海外人气赏。2011年，FAMI通2011年度大赏，最佳女主角奖。唯一在游戏界和动画界取得该成就的女性声优。\r\n2013年，NewType动画大赏2013 女性声优赏。\r\n2015年，获得第九届声优奖助演女声优赏，同年8月1日从Mausu Promotion移籍至青二事务所。\r\n\r\n为人沉着低调，甚至到了被以为是情绪低落的地步，即使是大合照亦少见笑容，也极少见出现于其他声优网志之中。做事认真，由于资历老实力好做事又一板一眼，所以往往在录音室甚至要指导其他声优的演出，因此被田中理惠封为『座长』。\r\n和坂本真绫一样，即使在大学时还是有参与工作，而且其工作的密度完全无法想像直到2008年四月之前还是大学生。 并没有受过正统声优学校训练，而被前辈冰上恭子以至事务所的吹替系前辈作演技指导，可说是边做边学。\r\n2008年3月大学毕业。学习勤奋刻苦的她以优异的成绩毕业，之前她仅两年内就拿到了100以上的高学分，大学四年间，她声优活动与兼顾学业做到两不耽误。\r\n自心之图书馆起便经常与斋藤千和共演，由于出道年份来说泽城很早就出道，所以往往出现明明年纪比她大的声优却要叫她前辈的有趣事。\r\n由于和真田麻美一起出道，因此二人公私之间的感情非常要好，也是低调的泽城少数私交较深的同行。和名冢佳织、小清水亚美、三瓶由布子因一同出演《强袭魔女》而交好。和同出身于东京都的下野纮有着类似于青梅竹马一样的关系。此外，和水树奈奈关系也不错，后者曾邀请泽城到新宿KOMA剧场参演舞台剧，以庆祝泽城大学毕业，两人还曾一同去屋久岛两日一夜游。\r\n\r\n家庭成员是父母和一个弟弟，弟弟是演员和声优泽城千春，喜欢西方古典乐，会在泡澡时看书。其实名字是叫做泽城幸，其原因是父亲是中岛美雪的歌迷，所以就按照「みゆき」（MIYUKI）这个读音给她取名字意为「幸」，因此她的名字应该汉字写作「泽城幸」。有趣的是，在父亲给她取名的时候，日本人由于有时候用汉字可以标记的假名太多，所以经常混淆。她的母亲曾经反驳父亲道，叫「幸」不是应该用「さち（SACHI）」的读音吗？\r\n\r\n2014年6月2日，在自己的博客宣告了与圈外男性结婚的喜讯。\r\n2018年6月28日，因要产前休养、以及产后育儿相关事情，宣布从夏天开始暂停声优工作，在同年的11月5日产后复出。",
                    "locked": false
                }
            ]
        },
        {
            "id": 13204,
            "name": "ホライゾン・アリアダスト",
            "type": 1,
            "images": {
                "large": "https://lain.bgm.tv/pic/crt/l/92/42/13204_crt_ZjPNZ.jpg",
                "medium": "https://lain.bgm.tv/r/400/pic/crt/l/92/42/13204_crt_ZjPNZ.jpg",
                "small": "https://lain.bgm.tv/r/100/pic/crt/l/92/42/13204_crt_ZjPNZ.jpg",
                "grid": "https://lain.bgm.tv/pic/crt/g/92/42/13204_crt_ZjPNZ.jpg"
            },
            "relation": "主角",
            "actors": [
                {
                    "id": 4421,
                    "name": "茅原実里",
                    "type": 1,
                    "career": [
                        "artist",
                        "seiyu"
                    ],
                    "images": {
                        "large": "https://lain.bgm.tv/pic/crt/l/3f/bc/4421_prsn_uGz8w.jpg?r=1554891438",
                        "medium": "https://lain.bgm.tv/r/400/pic/crt/l/3f/bc/4421_prsn_uGz8w.jpg?r=1554891438",
                        "small": "https://lain.bgm.tv/r/100/pic/crt/l/3f/bc/4421_prsn_uGz8w.jpg?r=1554891438",
                        "grid": "https://lain.bgm.tv/pic/crt/g/3f/bc/4421_prsn_uGz8w.jpg?r=1554891438"
                    },
                    "short_summary": "茅原实里（1980年11月18日－），日本女性声优、歌手。枥木县宇都宫市出生，埼玉县成长。天蝎座、血型B型。所属事务所为“M-Peace”，唱片公司为Lantis。身高157厘米，家中有姐弟等三人，排行老二，昵称为みのりん（Minorin）。\r\n\r\n主要饰演的代表角色为电视动画天上天下的枣亚夜、凉宫春日的忧郁的长门有希、幸运☆星的岩崎南、南家三姊妹系列作的南千秋、初音岛II（D.C. II: Da Capo II）系列作的白河奈奈佳、食灵~零的土宫神乐、境界的彼方的名濑美月等。官方的歌迷俱乐部网站为“m.s.s”（minori smile seasons）（实里的微笑季）。\r\n\r\n以出道仅六年之短时间，在2010年5月30日，成为声优史上第六位登上歌手最高殿堂日本武道馆举行个人演唱会的女声优，歌唱能力备受肯定。\r\n\r\n2013年3月31日，与Avex Planning&Development合约到期，并离开APD，FanClub“m.s.s”也随即解散。2013年4月1日，原Blog“minorhythm”关闭，开设新Blog“Smile Days”。2013年4月2日，建立个人事务所“M-Peace”。\r\n2019年4月1日，移籍HORIPRO INTERNATIONAL。",
                    "locked": false
                }
            ]
        },
        {
            "id": 13207,
            "name": "葵・トーリ",
            "type": 1,
            "images": {
                "large": "https://lain.bgm.tv/pic/crt/l/2a/e4/13207_crt_q3Ofy.jpg",
                "medium": "https://lain.bgm.tv/r/400/pic/crt/l/2a/e4/13207_crt_q3Ofy.jpg",
                "small": "https://lain.bgm.tv/r/100/pic/crt/l/2a/e4/13207_crt_q3Ofy.jpg",
                "grid": "https://lain.bgm.tv/pic/crt/g/2a/e4/13207_crt_q3Ofy.jpg"
            },
            "relation": "主角",
            "actors": [
                {
                    "id": 3818,
                    "name": "福山潤",
                    "type": 1,
                    "career": [
                        "artist",
                        "seiyu"
                    ],
                    "images": {
                        "large": "https://lain.bgm.tv/pic/crt/l/bf/00/3818_prsn_vlWlO.jpg?r=1669378022",
                        "medium": "https://lain.bgm.tv/r/400/pic/crt/l/bf/00/3818_prsn_vlWlO.jpg?r=1669378022",
                        "small": "https://lain.bgm.tv/r/100/pic/crt/l/bf/00/3818_prsn_vlWlO.jpg?r=1669378022",
                        "grid": "https://lain.bgm.tv/pic/crt/g/bf/00/3818_prsn_vlWlO.jpg?r=1669378022"
                    },
                    "short_summary": "福山润（1978年11月26日－）是一名日本男性声优。大阪府高槻市出身。2000年于21岁时加入PRODUCTION baobab，2011年退出和PRODUCTION baobab，并与森川智之共同设立AXL ONE事务所。2018年3月31日，与立花慎之介一起离开AXL ONE；同年4月1日，与立花合伙成立小型事务所“BLACK SHIP”。\r\n初试啼声的动画作品是1998年的《罗德斯岛战记》。初次担任主角的动画作品是2000年到2001年的《无敌王TRI-ZENON》，饰演神威章。此部作品同时也是无职身分的福山润再次以声优身分回归声优界的复归代表作。而令福山润真正登上事业上第一次颠峰的角色，则是《反叛的鲁路修》中的腹黑王子鲁路修，他就是凭着这个角色而获得了第一回声优悬赏奖的最佳男声优。",
                    "locked": false
                }
            ]
        }
    ]
}