{
    "id": 11257,
    "name": "エリュシア・デ・ルート・イーマ",
    "type": 1,
    "images": {
        "large": "https://lain.bgm.tv/pic/crt/l/56/a2/11257_crt_ZbdIO.jpg?r=1378924067",
        "medium": "https://lain.bgm.tv/r/400/pic/crt/l/56/a2/11257_crt_ZbdIO.jpg?r=1378924067",
        "small": "https://lain.bgm.tv/r/100/pic/crt/l/56/a2/11257_crt_ZbdIO.jpg?r=1378924067",
        "grid": "https://lain.bgm.tv/pic/crt/g/56/a2/11257_crt_ZbdIO.jpg?r=1378924067"
    },
    "summary": "新恶魔，隶属于地狱的冥界法治省极东支局的“驱魂队”，阶级为三等公务魔。在进入驱魂队之前当了300年的地狱扫除人员，目前是驱魂队的新人。头上戴有骷髅的发饰，这个发饰也是驱魂探测器，身上缠着的羽衣可以变化成各种东西，覆盖自己可以隐藏气息不让他人查觉。总是随身带着一把扫把，因为一旦离开身边会感到不自在。300年的扫除经验让艾鲁西会习惯性的打扫且技术非常完美。有着傻乎乎的性格，既冒失有时候还是个爱哭鬼，令桂马曾对恶魔有很强烈的误解，桂马将她称为“BUG恶魔”。\r\n    为了方便和桂马一起行动，假装成桂马父亲的私生女（此事引起桂马母亲的强烈误会，让她想和桂马父亲离婚，由于桂马父亲出差尚未回国，真相至今仍然无法揭开。），和桂马同住在一个屋檐下。并以桂马妹妹的身分转入桂马班上，目前已经相当习惯人间的生活。\r\n    非常的敬重桂马，听到别人对桂马的歧视会感到不高兴。起初假扮成桂马的异母妹妹时，被桂马的B.M.W.定义给反对。尽管如此，最后在艾鲁西的各种努力下还是让桂马认同艾鲁西能够成为他的妹妹。会有着上课时传字条给桂马的可爱举动，也可以从字条的内容看出艾鲁西对桂马的感情非常微妙。对于桂马拿自己当练习告白的对象会非常的害羞且不知所措。称呼桂马为“神大人”或“神大人哥哥”。\r\n    在刊篇时看到消防车的介绍之后不知为何对其着迷，之后一看到消防车就会陷入狂热状态。",
    "locked": false,
    "infobox": [
        {
            "key": "简体中文名",
            "value": "艾利由西亚·D·鲁德·伊玛"
        },
        {
            "key": "别名",
            "value": [
                {
                    "k": "第二中文名",
                    "v": "艾鲁西"
                },
                {
                    "k": "英文名",
                    "v": "Elsea De Lute Irma"
                },
                {
                    "k": "昵称",
                    "v": "エルシィ"
                }
            ]
        },
        {
            "key": "性别",
            "value": "女"
        },
        {
            "key": "生日",
            "value": "3月14日"
        },
        {
            "key": "身高",
            "value": "159cm（含发髻）"
        },
        {
            "key": "体重",
            "value": "44kg"
        },
        {
            "key": "BWH",
            "value": "B83/W58/H84"
        }
    ],
    "gender": "female",
    "blood_type": null,
    "birth_year": null,
    "birth_mon": 3,
    "birth_day": 14,
    "stat": {
        "comments": 48,
        "collects": 172
    },
    "anime_ids": [
        10739,
        5976
    ]
}