{
    "id": 266,
    "name": "金色の闇/ダークネス",
    "type": 1,
    "images": {
        "large": "https://lain.bgm.tv/pic/crt/l/59/70/266_crt_444p0.jpg",
        "medium": "https://lain.bgm.tv/r/400/pic/crt/l/59/70/266_crt_444p0.jpg",
        "small": "https://lain.bgm.tv/r/100/pic/crt/l/59/70/266_crt_444p0.jpg",
        "grid": "https://lain.bgm.tv/pic/crt/g/59/70/266_crt_444p0.jpg"
    },
    "summary": "宇宙中最危险的刺客。外表是很可爱的金色头发且穿黑色战斗服装的美少女（小女孩，在OVA第1话中和漫画第100话中曾用变身能力使自己身材变得更好，但被梨斗看见而变回原貌），平常总摆著一张扑克脸。因拥有能将自己身上的任何器官转换成武器的能力，故被称为“全身武器”和自身的体内带有纳米机械。受予以假情报的委托人拉可斯波的委托，到地球夺走梨斗的性命。意识到被拉可斯波利用的事，遭拉可斯波取消委托。由于被菈菈救起，所以即使菈菈笨拙，但对她仍抱著好意。\r\n委托泡汤之后，以“自己不会错失猎物”、“梨斗还是目标”为理由，继续观察梨斗。\r\n经常面无表情，内心对感情这一词不太理解。但对“H（色情）”的事情敏感（有时因为H的误会，而用头发变成的大拳头单打无辜的梨斗）。当与梨斗等人相处久了，感情变得较显露，因周围人的关系，以及对梨斗有些微感觉，开始明白所谓的感情。不但爱吃鲷鱼烧和意外地对食有兴趣，也喜好阅读。讨厌黏黏滑滑的东西。\r\n经常喂猫。\r\n被菈菈、美柑及鲷鱼烧老板等人叫“小暗”，本名与《黑猫》中的“伊芙”相同。有暗示自己是孤独之身的发言。当初来到地球劝告美柑不要太接近自己和与自己亲密，但慢慢地也肯与她做朋友。\r\n小暗的太空船的名称是露娜提克号（露娜提克号的名字来源据说是《黑猫》中的伊芙母亲的姓氏，即是本剧角色提亚悠的姓氏。）\r\n不论是造型、能力、性格、角色背景（还有原名）还有配音员都与矢吹健太朗前作《黑猫》中的伊芙（イヴ）大致相同，最为明显不同的是小暗成为了孤独冷酷的杀手，而《黑猫》中的伊芙后来的性格温柔也不喜杀生被史恩和托雷影响想成为赏金猎人去捕抓坏人。\r\n在漫画版‘Darkness’中，成为主要女主角，与芽亚是姐妹。在本作小暗正式成为彩南高中的学生，也终于鼓起勇气面对提亚悠。\r\n自身的黑色衣服能够从观察路人的服装而作出变化（就好像是沛凯一样能自由的变化自身），但是变身只能变一段时间，不能保持长期变身的时间。\r\n在漫画149话中从库洛口中得知金色暗影是由一名叫蒂亚优博士所制做的生物兵器和一直受用于一个组织，但是后来组织被库洛消灭了因而得了自由。\r\n在动画第二季第十一集时因为被擅自喝冰箱剩馀可乐而醉的希莉奴喷洒花粉而与梨斗约会，当时希望与梨斗接吻，但最终被梨斗指正不是真正喜欢而拒绝。\r\n官方女主角总选举获得“想要成为自己家人的角色”第3名、“偶像团体”第3名、“想要进入身体一天的角色”第1名、“想要做自己恋人的角色”第3名。",
    "locked": false,
    "infobox": [
        {
            "key": "简体中文名",
            "value": "金色暗影/DARKNESS"
        },
        {
            "key": "别名",
            "value": [
                {
                    "k": "英文名",
                    "v": "Golden Darkness"
                },
                {
                    "k": "日文名",
                    "v": "金色の闇 / ダークネス"
                },
                {
                    "k": "纯假名",
                    "v": "こんじきのやみ"
                },
                {
                    "k": "罗马字",
                    "v": "Konjiki no Yami"
                },
                {
                    "k": "昵称",
                    "v": "小暗"
                },
                {
                    "k": "本名",
                    "v": "伊芙"
                }
            ]
        },
        {
            "key": "性别",
            "value": "女"
        },
        {
            "key": "生日",
            "value": "12月24日"
        },
        {
            "key": "血型",
            "value": "AB"
        },
        {
            "key": "身高",
            "value": "153cm"
        },
        {
            "key": "体重",
            "value": [
                {
                    "k": "金色暗影",
                    "v": "45kg"
                },
                {
                    "k": "DARKNESS",
                    "v": "50kg（含角和指甲）"
                }
            ]
        },
        {
            "key": "BWH",
            "value": "B75-W52-H77"
        },
        {
            "key": "专长",
            "value": [
                {
                    "k": "金色暗影",
                    "v": "变身能力、格斗"
                },
                {
                    "k": "DARKNESS",
                    "v": "变身能力"
                }
            ]
        },
        {
            "key": "喜欢",
            "value": [
                {
                    "k": "金色暗影",
                    "v": "鲷鱼烧、阅读"
                },
                {
                    "k": "DARKNESS",
                    "v": "色色的事、湿湿滑滑的东西、结城梨斗"
                }
            ]
        },
        {
            "key": "不擅长",
            "value": [
                {
                    "k": "金色暗影",
                    "v": "湿湿滑滑的东西"
                },
                {
                    "k": "DARKNESS",
                    "v": "纠缠不休的东西"
                }
            ]
        },
        {
            "key": "收到会开心的物品",
            "value": [
                {
                    "k": "金色暗影",
                    "v": "只要是朋友送的，什么都喜欢"
                },
                {
                    "k": "DARKNESS",
                    "v": "结城梨斗的性命"
                }
            ]
        },
        {
            "key": "喜欢的游玩地点",
            "value": [
                {
                    "k": "金色暗影",
                    "v": "大型书店、风景好的地方"
                },
                {
                    "k": "DARKNESS",
                    "v": "高大的建筑物或宽敞的地方"
                }
            ]
        },
        {
            "key": "喜欢的电影类型",
            "value": [
                {
                    "k": "金色暗影",
                    "v": "家庭剧、时代剧"
                },
                {
                    "k": "DARKNESS",
                    "v": "小孩子不能观赏的电影"
                }
            ]
        }
    ],
    "gender": "female",
    "blood_type": 3,
    "birth_year": null,
    "birth_mon": 12,
    "birth_day": 24,
    "stat": {
        "comments": 64,
        "collects": 551
    },
    "anime_ids": [
        37694,
        120763
    ]
}