{
    "id": 42435,
    "name": "桜坂しずく",
    "type": 1,
    "images": {
        "large": "https://lain.bgm.tv/pic/crt/l/d4/c7/42435_crt_J1TB2.jpg?r=1703253658",
        "medium": "https://lain.bgm.tv/r/400/pic/crt/l/d4/c7/42435_crt_J1TB2.jpg?r=1703253658",
        "small": "https://lain.bgm.tv/r/100/pic/crt/l/d4/c7/42435_crt_J1TB2.jpg?r=1703253658",
        "grid": "https://lain.bgm.tv/pic/crt/g/d4/c7/42435_crt_J1TB2.jpg?r=1703253658"
    },
    "summary": "みなさん、こんにちは。桜坂しずくです。\r\n私はお芝居をすることが大好きで、学校では演劇部に所属しています。\r\n衣装とかも自分たちで作って、定期的に公演もしてるんですよ。\r\nそれから、演劇の役に立つかもと思ってスクールアイドルの活動も行なっていたのですが、\r\n今回、尊敬する先輩に、\r\n『スクールアイドルとして、もうひとつ上のステージを目指してみようよ』\r\nと誘われて、私、気づいたんです。\r\n演劇もスクールアイドルも、観に来てくれた人を楽しませて、感動させて、\r\nそして笑顔になってもらう為の表現の場、一緒なんだってことに。\r\nだから、もっと積極的にスクールアイドル活動に挑戦してみようと思いました！\r\n演劇部で鍛えた表現力を武器に、皆さんを笑顔にできるよう精進していきます。\r\nまだまだ不束者な私ですが、私の精一杯の表現を観に来てくれたら嬉しいです！\r\nよろしくお願いします！\r\n\r\nKlab旗下的手机音乐节奏社交卡牌游戏《LoveLive! 学园偶像祭》登场人物，从青蓝高校转入音乃木坂。\r\n演剧部部员，认为通过参加校园偶像活动能够为表演提供参考。\r\n\r\n2014年4月举办的第1次转学生总选举排名第3；\r\n2015年6月举办的第2次转学生总选举排名第6；\r\n2017年1月举办的第3次转学生总选举排名第2。\r\n\r\n2017年5月18日，与原有N卡近江彼方、艾玛和六名新角色一起被公布为学园偶像祭新企划Perfect Dream Project的成员之一。",
    "locked": false,
    "infobox": [
        {
            "key": "简体中文名",
            "value": "樱坂雫"
        },
        {
            "key": "别名",
            "value": [
                {
                    "k": "英文名",
                    "v": "Shizuku Osaka"
                },
                {
                    "k": "日文名",
                    "v": "桜坂 しずく"
                },
                {
                    "k": "纯假名",
                    "v": "おうさか しずく"
                },
                {
                    "k": "罗马字",
                    "v": "Ōsaka Shizuku"
                },
                {
                    "k": "昵称",
                    "v": "しず子"
                }
            ]
        },
        {
            "key": "性别",
            "value": "女"
        },
        {
            "key": "生日",
            "value": "4月3日"
        },
        {
            "key": "血型",
            "value": "A"
        },
        {
            "key": "身高",
            "value": "157cm"
        },
        {
            "key": "BWH",
            "value": "80/58/83"
        },
        {
            "key": "学校",
            "value": "青藍高校→虹ヶ咲学園"
        },
        {
            "key": "学年",
            "value": "1年级"
        },
        {
            "key": "兴趣",
            "value": "観劇"
        },
        {
            "key": "代表色",
            "value": "亮蓝色"
        },
        {
            "key": "印象标志",
            "value": "水滴"
        },
        {
            "key": "歌曲印象风格",
            "value": "清楚 / 乙女"
        },
        {
            "key": "分组",
            "value": "A・ZU・NA"
        }
    ],
    "gender": "female",
    "blood_type": 1,
    "birth_year": null,
    "birth_mon": 4,
    "birth_day": 3,
    "stat": {
        "comments": 27,
        "collects": 111
    },
    "anime_ids": [
        296659,
        335579
    ]
}